<xml>
    <object name="GPSSettings" singleinstance="true" settings="true">
        <description>Settings for the GPS</description>
        <field name="DataProtocol" units="" type="enum" elements="1" options="NMEA,UBX" defaultvalue="UBX"/>
        <access gcs="readwrite" flight="readwrite"/>
        <telemetrygcs acked="true" updatemode="onchange" period="0"/>
        <telemetryflight acked="true" updatemode="onchange" period="0"/>
        <logging updatemode="manual" period="0"/>
    </object>
</xml>
